README.rst
setup.py
src/wig3j.f
src/xpol.f90
src/xpol.h
src/xpol_fits_param.h
xpol/__init__.py
xpol/xpol.py
xpol/xpol_sym.py
xpol.egg-info/PKG-INFO
xpol.egg-info/SOURCES.txt
xpol.egg-info/dependency_links.txt
xpol.egg-info/requires.txt
xpol.egg-info/top_level.txt