Metadata-Version: 1.0
Name: xpol
Version: 1.6.1
Summary: XPOL cross power-spectrum estimator
Home-page: UNKNOWN
Author: Matthieu Tristram
Author-email: tristram@lal.in2p3.fr
License: UNKNOWN
Platform: UNKNOWN
